{
    "metadata": {
        "namespace": "ItemConsts"
    },
    "items": {
        "potions": {
            "light_healing": {
                "id": 0,
                "name": "POT_OF_LIGHT_HEAL"
            },
            "moderate_healing": {
                "id": 1,
                "name": "POT_OF_MOD_HEAL"
            },
            "full_healing": {
                "id": 2,
                "name": "POT_OF_FULL_HEAL"
            },
            "cure_poison": {
                "id": 3,
                "name": "POT_OF_CURE_POISON"
            },
            "berserk_strength": {
                "id": 4,
                "name": "POT_OF_BERSERK_STR"
            },
            "speed": {
                "id": 5,
                "name": "POT_OF_SPEED"
            },
            "hardiness": {
                "id": 6,
                "name": "POT_OF_HARDINESS"
            },
            "extra_attacks": {
                "id": 7,
                "name": "POT_OF_EXTRA_ATTACKS"
            },
            "poison": {
                "id": 8,
                "name": "POT_OF_POISON"
            },
            "death": {
                "id": 9,
                "name": "POT_OF_DEATH"
            }
        },
        "scrolls": {
            "identify": {
                "id": 0,
                "name": "SCROLL_OF_IDENT"
            },
            "identify_all": {
                "id": 1,
                "name": "SCROLL_OF_IDENT_ALL"
            },
            "magic_map": {
                "id": 2,
                "name": "SCROLL_OF_MAGIC_MAP"
            },
            "decurse": {
                "id": 3,
                "name": "SCROLL_OF_DECURSE"
            },
            "decurse_all": {
                "id": 4,
                "name": "SCROLL_OF_DECURSE_ALL"
            },
            "teleport": {
                "id": 5,
                "name": "SCROLL_OF_TELEPORT"
            },
            "recall": {
                "id": 6,
                "name": "SCROLL_OF_RECALL"
            },
            "summon_item": {
                "id": 7,
                "name": "SCROLL_OF_SUMMON_ITEM"
            },
            "darkness": {
                "id": 8,
                "name": "SCROLL_OF_DARKNESS"
            },
            "forget_area": {
                "id": 9,
                "name": "SCROLL_OF_FORGET_AREA"
            },
            "curse": {
                "id": 10,
                "name": "SCROLL_OF_CURSE"
            }
        }
    }
}